reeve_python_sdk/__init__.py
reeve_python_sdk/auth.py
reeve_python_sdk/client.py
reeve_python_sdk/exceptions.py
reeve_python_sdk/face.py
reeve_python_sdk/models.py
reeve_python_sdk/person.py
reeve_python_sdk/subject.py
reeve_python_sdk-0.1.0.dist-info/licenses/LICENSE.txt
reeve_python_sdk-0.1.0.dist-info/METADATA
reeve_python_sdk-0.1.0.dist-info/WHEEL
reeve_python_sdk-0.1.0.dist-info/top_level.txt
reeve_python_sdk-0.1.0.dist-info/RECORD
