Metadata-Version: 2.4
Name: reeve_python_sdk
Version: 0.1.0
Summary: Python SDK for the Reeve API - A facial recognition service for person identification and verification
Home-page: https://github.com/qbit-codes/reeve-python-sdk/
Author: muhammedsaidckr
Author-email: muhammedsaidckr@gmail.com
License: MIT
Project-URL: Documentation, https://github.com/qbit-codes/reeve-python-sdk/
Project-URL: Source, https://github.com/qbit-codes/reeve-python-sdk/
Project-URL: Tracker, https://github.com/qbit-codes/reeve-python-sdk/issues
Platform: any
Classifier: Development Status :: 4 - Beta
Classifier: Programming Language :: Python
License-File: LICENSE.txt
Requires-Dist: importlib-metadata; python_version < "3.8"
Requires-Dist: aiohttp>=3.8.0
Requires-Dist: aiofiles>=23.0.0
Requires-Dist: python-dateutil>=2.8.0
Provides-Extra: testing
Requires-Dist: setuptools; extra == "testing"
Requires-Dist: pytest; extra == "testing"
Requires-Dist: pytest-cov; extra == "testing"
Requires-Dist: pytest-asyncio>=0.21.0; extra == "testing"
Requires-Dist: aioresponses>=0.7.0; extra == "testing"
Dynamic: license-file
